{
  "name": "Light Blossom Purple",
  "description": "A beautiful light blossom purple theme, made for people who love blossom but prefer a brighter interface.",
  "version": "1",
  "authors": [
    {
      "name": "kmmiio99o.dev",
      "id": "879393496627306587"
    }
  ],
  "semanticColors": {
    "ANDROID_RIPPLE": ["#d8b4f8"],
    "CHAT_BACKGROUND": ["#f9f4fe"],
    "BACKGROUND_ACCENT": ["#c084fc"],
    "BACKGROUND_FLOATING": ["#ffffff"],
    "BACKGROUND_MENTIONED": ["#c084fc33"],
    "BACKGROUND_MENTIONED_HOVER": ["#c084fc4d"],
    "SCROLLBAR_THIN_THUMB": ["#d8b4f8"],
    "SCROLLBAR_THIN_TRACK": ["transparent"],
    "SCROLLBAR_AUTO_THUMB": ["#d8b4f8"],
    "SCROLLBAR_AUTO_TRACK": ["transparent"],
    "CHANNELTEXTAREA_BACKGROUND": ["#ffffff"],
    "REDESIGN_ACTIVITY_CARD_BACKGROUND": ["#f9f4fe"],
    "REDESIGN_ACTIVITY_CARD_BACKGROUND_PRESSED": ["#d8b4f8"],
    "CHANNELS_DEFAULT": ["#7c3aed"],
    "BACKGROUND_MESSAGE_HOVER": ["hsla(270, 70%, 90%, 0.3)"],
    "BACKGROUND_NESTED_FLOATING": ["#ffffff"],
    "BACKGROUND_MOBILE_PRIMARY": ["#ffffff"],
    "BACKGROUND_MOBILE_SECONDARY": ["#f9f4fe"],
    "BACKGROUND_MODIFIER_ACCENT": ["hsla(270, 70%, 90%, 0.3)"],
    "BACKGROUND_MODIFIER_ACTIVE": ["hsla(270, 70%, 85%, 0.5)"],
    "BACKGROUND_MODIFIER_HOVER": ["hsla(270, 70%, 90%, 0.3)"],
    "BACKGROUND_MODIFIER_SELECTED": ["hsla(270, 70%, 85%, 0.5)"],
    "BACKGROUND_PRIMARY": ["#ffffff"],
    "BACKGROUND_SECONDARY": ["#f9f4fe"],
    "BACKGROUND_SECONDARY_ALT": ["#ede9fe"],
    "BACKGROUND_TERTIARY": ["#ddd6fe"],
    "BG_BASE_PRIMARY": ["#ffffff"],
    "BG_BACKDROP": ["#ffffffb2"],
    "BG_BASE_SECONDARY": ["#ffffff"],
    "BG_BASE_TERTIARY": ["#f9f4fe"],
    "HOME_BACKGROUND": ["#f9f4fe"],
    "BORDER_FAINT": ["hsla(270, 70%, 90%, 0.3)"],
    "BORDER_STRONG": ["hsla(270, 50%, 80%, 0.5)"],
    "BORDER_SUBTLE": ["hsla(270, 50%, 80%, 0.5)"],
    "CARD_SECONDARY_BG": ["#ede9fe"],
    "CARD_PRIMARY_BG": ["#f9f4fe"],
    "CHANNEL_ICON": ["#7c3aed"],
    "EMBED_BACKGROUND": ["#ede9fe"],
    "HEADER_PRIMARY": ["#9333ea"],
    "HEADER_SECONDARY": ["#7c3aed"],
    "INTERACTIVE_ACTIVE": ["#9333ea"],
    "INTERACTIVE_HOVER": ["#9333ea"],
    "INTERACTIVE_MUTED": ["#7c3aed66"],
    "INTERACTIVE_NORMAL": ["#7c3aed"],
    "MENTION_BACKGROUND": ["#a855f733"],
    "MENTION_FOREGROUND": ["#a855f7"],
    "REDESIGN_BUTTON_SECONDARY_ALT_BACKGROUND": ["#ede9fe"],
    "REDESIGN_BUTTON_SECONDARY_BACKGROUND": ["#ede9fe"],
    "REDESIGN_BUTTON_SECONDARY_BORDER": ["hsla(270, 50%, 80%, 0.5)"],
    "REDESIGN_BUTTON_DANGER_BACKGROUND": ["#9333ea"],
    "REDESIGN_CHANNEL_CATEGORY_NAME_TEXT": ["#7c3aed"],
    "REDESIGN_CHANNEL_NAME_TEXT": ["#9333ea"],
    "REDESIGN_CHAT_INPUT_BACKGROUND": ["#ffffff"],
    "SPOILER_HIDDEN_BACKGROUND": ["#ede9fe"],
    "STATUS_DANGER": ["#9333ea"],
    "STATUS_DANGER_BACKGROUND": ["#9333ea"],
    "STATUS_DANGER_TEXT": ["#ffffff"],
    "POLLS_NORMAL_FILL_HOVER": ["#ede9fe"],
    "POLLS_NORMAL_IMAGE_BACKGROUND": ["#ede9fe"],
    "POLLS_VICTOR_FILL": ["#c084fc80"],
    "TEXT_LINK": ["#9333ea"],
    "TEXT_MUTED": ["#7c3aed66"],
    "TEXT_NORMAL": ["#7c3aed"],
    "TEXT_PRIMARY": ["#9333ea"],
    "TEXT_SECONDARY": ["#7c3aed"],
    "BG_MOD_FAINT": ["hsla(270, 70%, 90%, 0.3)"],
    "KEYBOARD": ["#ffffff"],
    "BACKGROUND_MODIFIER_ACCEPT": ["#c084fc33"],
    "BACKGROUND_MODIFIER_ACCEPT_HOVER": ["#c084fc4d"],
    "AUTOMOD_QUEUED_FOR_REVIEW_BACKGROUND": ["#a855f733"],
    "AUTOMOD_QUEUED_FOR_REVIEW_BACKGROUND_HOVER": ["#a855f74d"]
  },
  "rawColors": {
    "BLUE_260": "#d8b4f8",
    "BLUE_300": "#d8b4f8",
    "BLUE_330": "#d8b4f8",
    "BLUE_345": "#d8b4f8",
    "BLUE_360": "#d8b4f8",
    "BLUE_400": "#d8b4f8",
    "BLUE_430": "#d8b4f8",
    "BLUE_460": "#d8b4f8",
    "BLUE_500": "#d8b4f8",
    "BLUE_530": "#d8b4f8",
    "BLUE_560": "#d8b4f8",
    "BLUE_600": "#d8b4f8",
    "BLUE_630": "#d8b4f8",
    "BLUE_660": "#d8b4f8",
    "BLUE_700": "#d8b4f8",
    "BLACK_500": "#ffffffb2",
    "BRAND_200": "#9333ea",
    "BRAND_260": "#9333ea",
    "BRAND_300": "#9333ea",
    "BRAND_330": "#9333ea",
    "BRAND_345": "#9333ea",
    "BRAND_360": "#9333ea",
    "BRAND_400": "#9333ea",
    "BRAND_430": "#9333ea",
    "BRAND_460": "#9333ea",
    "BRAND_500": "#9333ea",
    "BRAND_530": "#9333ea",
    "BRAND_560": "#9333ea",
    "BRAND_600": "#9333ea",
    "BRAND_630": "#9333ea",
    "BRAND_660": "#9333ea",
    "BRAND_700": "#9333ea",
    "BRAND_730": "#9333ea",
    "PLUM_1": "#9333ea",
    "PLUM_10": "#7c3aed",
    "PLUM_11": "#7c3aed",
    "PLUM_13": "#7c3aed",
    "PLUM_15": "#9333ea",
    "PLUM_16": "#f9f4fe",
    "PLUM_17": "#ffffff",
    "PLUM_18": "#f9f4fe",
    "PLUM_19": "#f9f4fe",
    "PLUM_20": "#ffffff",
    "PLUM_21": "#f9f4fe",
    "PLUM_22": "#f9f4fe",
    "PLUM_24": "#ffffff",
    "PLUM_25": "#ffffff",
    "PLUM_3": "#9333ea",
    "PLUM_4": "#9333ea",
    "PLUM_6": "#9333ea",
    "PLUM_9": "#7c3aed",
    "PRIMARY_100": "#9333ea",
    "PRIMARY_200": "#9333ea",
    "PRIMARY_300": "#9333ea",
    "PRIMARY_330": "#9333ea",
    "PRIMARY_360": "#9333ea",
    "PRIMARY_400": "#9333ea",
    "PRIMARY_460": "#ede9fe",
    "PRIMARY_500": "#9333ea",
    "PRIMARY_530": "#9333ea",
    "PRIMARY_600": "#ffffff",
    "PRIMARY_630": "#f9f4fe",
    "PRIMARY_645": "#ffffff",
    "PRIMARY_660": "#f9f4fe",
    "PRIMARY_700": "#f9f4fe",
    "PRIMARY_730": "#7c3aed",
    "PRIMARY_800": "#f9f4fe",
    "GREEN_260": "#c084fc",
    "GREEN_300": "#c084fc",
    "GREEN_330": "#c084fc",
    "GREEN_345": "#c084fc",
    "GREEN_360": "#c084fc",
    "GREEN_400": "#c084fc",
    "GREEN_430": "#c084fc",
    "GREEN_460": "#c084fc",
    "GREEN_500": "#c084fc",
    "GREEN_530": "#c084fc",
    "GREEN_560": "#c084fc",
    "GREEN_600": "#c084fc",
    "GREEN_630": "#c084fc",
    "GREEN_660": "#c084fc",
    "GREEN_700": "#c084fc",
    "GUILD_BOOSTING_PINK": "#9333ea",
    "GUILD_BOOSTING_PURPLE": "#9333ea",
    "GUILD_BOOSTING_PURPLE_FOR_GRADIENTS": "#9333ea",
    "RED_260": "#9333ea",
    "RED_300": "#9333ea",
    "RED_330": "#9333ea",
    "RED_345": "#9333ea",
    "RED_360": "#9333ea",
    "RED_400": "#9333ea",
    "RED_430": "#9333ea",
    "RED_460": "#9333ea",
    "RED_500": "#9333ea",
    "RED_530": "#9333ea",
    "RED_560": "#9333ea",
    "RED_600": "#9333ea",
    "RED_630": "#9333ea",
    "RED_660": "#9333ea",
    "RED_700": "#9333ea",
    "ROLE_DEFAULT": "#7c3aed",
    "ORANGE_260": "#d8b4f8",
    "ORANGE_300": "#d8b4f8",
    "ORANGE_330": "#d8b4f8",
    "ORANGE_345": "#d8b4f8",
    "ORANGE_360": "#d8b4f8",
    "ORANGE_400": "#d8b4f8",
    "ORANGE_430": "#d8b4f8",
    "ORANGE_460": "#d8b4f8",
    "ORANGE_500": "#d8b4f8",
    "ORANGE_530": "#d8b4f8",
    "ORANGE_560": "#d8b4f8",
    "ORANGE_600": "#d8b4f8",
    "ORANGE_630": "#d8b4f8",
    "ORANGE_660": "#d8b4f8",
    "ORANGE_700": "#d8b4f8",
    "YELLOW_260": "#d8b4f8",
    "YELLOW_300": "#d8b4f8",
    "YELLOW_330": "#d8b4f8",
    "YELLOW_345": "#d8b4f8",
    "YELLOW_360": "#d8b4f8",
    "YELLOW_400": "#d8b4f8",
    "YELLOW_430": "#d8b4f8",
    "YELLOW_460": "#d8b4f8",
    "YELLOW_500": "#d8b4f8",
    "YELLOW_530": "#d8b4f8",
    "YELLOW_560": "#d8b4f8",
    "YELLOW_600": "#d8b4f8",
    "YELLOW_630": "#d8b4f8",
    "YELLOW_660": "#d8b4f8",
    "YELLOW_700": "#d8b4f8",
    "WHITE_500": "#9333ea",
    "WHITE_630": "#7c3aed"
  },
  "plus": {
    "version": "0",
    "iconPack": "",
    "mentionLineColor": "#9333ea",
    "customOverlays": true,
    "icons": {
      "trash": "#9333ea",
      "TrashIcon": "#9333ea",
      "TriangleExclamationPointIcon": "#9333ea",
      "toast_copy_link": "#d8b4f8",
      "toast_copy_message": "#ffffff",
      "toast_image_saved": "#ffffff"
    }
  },
  "spec": 2
}
